{
    "name": "Illuminate\\Database\\DatabaseServiceProvider",
    "line": 7,
    "short_desc": "",
    "long_desc": "",
    "hint": null,
    "tags": [

    ],
    "namespace": "Illuminate\\Database",
    "file": "\/media\/sf_Code\/Laravel\/app\/vendor\/laravel\/framework\/src\/Illuminate\/Database\/DatabaseServiceProvider.php",
    "hash": "5e6ad310cf9e0cbd130b726cce0d69d94f5dbf90",
    "parent": "Illuminate\\Support\\ServiceProvider",
    "modifiers": 0,
    "is_trait": false,
    "is_interface": false,
    "aliases": {
        "Model": "Illuminate\\Database\\Eloquent\\Model",
        "ServiceProvider": "Illuminate\\Support\\ServiceProvider",
        "ConnectionFactory": "Illuminate\\Database\\Connectors\\ConnectionFactory"
    },
    "errors": [

    ],
    "interfaces": [

    ],
    "properties": [

    ],
    "methods": {
        "boot": {
            "name": "boot",
            "line": 14,
            "short_desc": "Bootstrap the application events.",
            "long_desc": "",
            "hint": [
                [
                    "void",
                    false
                ]
            ],
            "hint_desc": "",
            "tags": [

            ],
            "modifiers": "1",
            "is_by_ref": "",
            "exceptions": [

            ],
            "errors": [

            ],
            "parameters": [

            ]
        },
        "register": {
            "name": "register",
            "line": 26,
            "short_desc": "Register the service provider.",
            "long_desc": "",
            "hint": [
                [
                    "void",
                    false
                ]
            ],
            "hint_desc": "",
            "tags": [

            ],
            "modifiers": "1",
            "is_by_ref": "",
            "exceptions": [

            ],
            "errors": [

            ],
            "parameters": [

            ]
        }
    },
    "constants": [

    ]
}