{
    "name": "Illuminate\\Auth\\Reminders\\PasswordBroker",
    "line": 8,
    "short_desc": "",
    "long_desc": "",
    "hint": null,
    "tags": [

    ],
    "namespace": "Illuminate\\Auth\\Reminders",
    "file": "\/media\/sf_Code\/Laravel\/api-gen\/src\/Illuminate\/Auth\/Reminders\/PasswordBroker.php",
    "hash": "9c8963276aac1105872b14f6b0a9cfe9452e6211",
    "parent": null,
    "modifiers": 0,
    "is_trait": false,
    "is_interface": false,
    "aliases": {
        "Closure": "Closure",
        "Mailer": "Illuminate\\Mail\\Mailer",
        "Redirector": "Illuminate\\Routing\\Redirector",
        "UserProviderInterface": "Illuminate\\Auth\\UserProviderInterface"
    },
    "errors": [

    ],
    "interfaces": [

    ],
    "properties": [

    ],
    "methods": {
        "__construct": {
            "name": "__construct",
            "line": 55,
            "short_desc": "Create a new password broker instance.",
            "long_desc": "",
            "hint": [
                [
                    "void",
                    false
                ]
            ],
            "hint_desc": "",
            "tags": [

            ],
            "modifiers": "1",
            "is_by_ref": "",
            "exceptions": [

            ],
            "errors": [

            ],
            "parameters": {
                "reminders": {
                    "name": "reminders",
                    "line": 55,
                    "short_desc": "",
                    "long_desc": null,
                    "hint": [
                        [
                            "Illuminate\\Auth\\Reminders\\ReminderRepositoryInterface",
                            false
                        ]
                    ],
                    "tags": [

                    ],
                    "modifiers": "ReminderRepositoryInterface",
                    "default": null,
                    "is_by_ref": false
                },
                "users": {
                    "name": "users",
                    "line": 56,
                    "short_desc": "",
                    "long_desc": null,
                    "hint": [
                        [
                            "Illuminate\\Auth\\UserProviderInterface",
                            false
                        ]
                    ],
                    "tags": [

                    ],
                    "modifiers": "UserProviderInterface",
                    "default": null,
                    "is_by_ref": false
                },
                "redirect": {
                    "name": "redirect",
                    "line": 57,
                    "short_desc": "",
                    "long_desc": null,
                    "hint": [
                        [
                            "Illuminate\\Routing\\Redirector",
                            false
                        ]
                    ],
                    "tags": [

                    ],
                    "modifiers": "Redirector",
                    "default": null,
                    "is_by_ref": false
                },
                "mailer": {
                    "name": "mailer",
                    "line": 58,
                    "short_desc": "",
                    "long_desc": null,
                    "hint": [
                        [
                            "Illuminate\\Mail\\Mailer",
                            false
                        ]
                    ],
                    "tags": [

                    ],
                    "modifiers": "Mailer",
                    "default": null,
                    "is_by_ref": false
                },
                "reminderView": {
                    "name": "reminderView",
                    "line": 59,
                    "short_desc": "",
                    "long_desc": null,
                    "hint": [
                        [
                            "string",
                            false
                        ]
                    ],
                    "tags": [

                    ],
                    "modifiers": "",
                    "default": null,
                    "is_by_ref": false
                }
            }
        },
        "remind": {
            "name": "remind",
            "line": 75,
            "short_desc": "Send a password reminder to a user.",
            "long_desc": "",
            "hint": [
                [
                    "\\Illuminate\\Http\\RedirectResponse",
                    false
                ]
            ],
            "hint_desc": "",
            "tags": [

            ],
            "modifiers": "1",
            "is_by_ref": "",
            "exceptions": [

            ],
            "errors": [

            ],
            "parameters": {
                "credentials": {
                    "name": "credentials",
                    "line": 75,
                    "short_desc": "",
                    "long_desc": null,
                    "hint": [
                        [
                            "array",
                            false
                        ]
                    ],
                    "tags": [

                    ],
                    "modifiers": "array",
                    "default": null,
                    "is_by_ref": false
                },
                "callback": {
                    "name": "callback",
                    "line": 75,
                    "short_desc": "",
                    "long_desc": null,
                    "hint": [
                        [
                            "Closure",
                            false
                        ]
                    ],
                    "tags": [

                    ],
                    "modifiers": "Closure",
                    "default": "null",
                    "is_by_ref": false
                }
            }
        },
        "sendReminder": {
            "name": "sendReminder",
            "line": 105,
            "short_desc": "Send the password reminder e-mail.",
            "long_desc": "",
            "hint": [
                [
                    "void",
                    false
                ]
            ],
            "hint_desc": "",
            "tags": [

            ],
            "modifiers": "1",
            "is_by_ref": "",
            "exceptions": [

            ],
            "errors": [

            ],
            "parameters": {
                "user": {
                    "name": "user",
                    "line": 105,
                    "short_desc": "",
                    "long_desc": null,
                    "hint": [
                        [
                            "Illuminate\\Auth\\Reminders\\RemindableInterface",
                            false
                        ]
                    ],
                    "tags": [

                    ],
                    "modifiers": "RemindableInterface",
                    "default": null,
                    "is_by_ref": false
                },
                "token": {
                    "name": "token",
                    "line": 105,
                    "short_desc": "",
                    "long_desc": null,
                    "hint": [
                        [
                            "string",
                            false
                        ]
                    ],
                    "tags": [

                    ],
                    "modifiers": "",
                    "default": null,
                    "is_by_ref": false
                },
                "callback": {
                    "name": "callback",
                    "line": 105,
                    "short_desc": "",
                    "long_desc": null,
                    "hint": [
                        [
                            "Closure",
                            false
                        ]
                    ],
                    "tags": [

                    ],
                    "modifiers": "Closure",
                    "default": "null",
                    "is_by_ref": false
                }
            }
        },
        "reset": {
            "name": "reset",
            "line": 127,
            "short_desc": "Reset the password for the given token.",
            "long_desc": "",
            "hint": [
                [
                    "mixed",
                    false
                ]
            ],
            "hint_desc": "",
            "tags": [

            ],
            "modifiers": "1",
            "is_by_ref": "",
            "exceptions": [

            ],
            "errors": [

            ],
            "parameters": {
                "credentials": {
                    "name": "credentials",
                    "line": 127,
                    "short_desc": "",
                    "long_desc": null,
                    "hint": [
                        [
                            "array",
                            false
                        ]
                    ],
                    "tags": [

                    ],
                    "modifiers": "array",
                    "default": null,
                    "is_by_ref": false
                },
                "callback": {
                    "name": "callback",
                    "line": 127,
                    "short_desc": "",
                    "long_desc": null,
                    "hint": [
                        [
                            "Closure",
                            false
                        ]
                    ],
                    "tags": [

                    ],
                    "modifiers": "Closure",
                    "default": null,
                    "is_by_ref": false
                }
            }
        },
        "getUser": {
            "name": "getUser",
            "line": 210,
            "short_desc": "Get the user for the given credentials.",
            "long_desc": "",
            "hint": [
                [
                    "\\Illuminate\\Auth\\Reminders\\RemindableInterface",
                    false
                ]
            ],
            "hint_desc": "",
            "tags": [

            ],
            "modifiers": "1",
            "is_by_ref": "",
            "exceptions": [

            ],
            "errors": [

            ],
            "parameters": {
                "credentials": {
                    "name": "credentials",
                    "line": 210,
                    "short_desc": "",
                    "long_desc": null,
                    "hint": [
                        [
                            "array",
                            false
                        ]
                    ],
                    "tags": [

                    ],
                    "modifiers": "array",
                    "default": null,
                    "is_by_ref": false
                }
            }
        }
    },
    "constants": [

    ]
}