{
    "name": "Illuminate\\Routing\\UrlGenerator",
    "line": 9,
    "short_desc": "",
    "long_desc": "",
    "hint": null,
    "tags": [

    ],
    "namespace": "Illuminate\\Routing",
    "file": "\/media\/sf_Code\/Laravel\/api-gen\/src\/Illuminate\/Routing\/UrlGenerator.php",
    "hash": "fdc7da8d296f7c4fb95e032c735772e9ebfc2d73",
    "parent": null,
    "modifiers": 0,
    "is_trait": false,
    "is_interface": false,
    "aliases": {
        "InvalidArgumentException": "InvalidArgumentException",
        "Request": "Symfony\\Component\\HttpFoundation\\Request",
        "RequestContext": "Symfony\\Component\\Routing\\RequestContext",
        "RouteCollection": "Symfony\\Component\\Routing\\RouteCollection",
        "SymfonyGenerator": "Symfony\\Component\\Routing\\Generator\\UrlGenerator"
    },
    "errors": [

    ],
    "interfaces": [

    ],
    "properties": [

    ],
    "methods": {
        "__construct": {
            "name": "__construct",
            "line": 39,
            "short_desc": "Create a new URL Generator instance.",
            "long_desc": "",
            "hint": [
                [
                    "void",
                    false
                ]
            ],
            "hint_desc": "",
            "tags": [

            ],
            "modifiers": "1",
            "is_by_ref": "",
            "exceptions": [

            ],
            "errors": [

            ],
            "parameters": {
                "routes": {
                    "name": "routes",
                    "line": 39,
                    "short_desc": "",
                    "long_desc": null,
                    "hint": [
                        [
                            "Symfony\\Component\\Routing\\RouteCollection",
                            false
                        ]
                    ],
                    "tags": [

                    ],
                    "modifiers": "RouteCollection",
                    "default": null,
                    "is_by_ref": false
                },
                "request": {
                    "name": "request",
                    "line": 39,
                    "short_desc": "",
                    "long_desc": null,
                    "hint": [
                        [
                            "Symfony\\Component\\HttpFoundation\\Request",
                            false
                        ]
                    ],
                    "tags": [

                    ],
                    "modifiers": "Request",
                    "default": null,
                    "is_by_ref": false
                }
            }
        },
        "full": {
            "name": "full",
            "line": 51,
            "short_desc": "Get the full URL for the current request.",
            "long_desc": "",
            "hint": [
                [
                    "string",
                    false
                ]
            ],
            "hint_desc": "",
            "tags": [

            ],
            "modifiers": "1",
            "is_by_ref": "",
            "exceptions": [

            ],
            "errors": [

            ],
            "parameters": [

            ]
        },
        "current": {
            "name": "current",
            "line": 61,
            "short_desc": "Get the current URL for the request.",
            "long_desc": "",
            "hint": [
                [
                    "string",
                    false
                ]
            ],
            "hint_desc": "",
            "tags": [

            ],
            "modifiers": "1",
            "is_by_ref": "",
            "exceptions": [

            ],
            "errors": [

            ],
            "parameters": [

            ]
        },
        "previous": {
            "name": "previous",
            "line": 71,
            "short_desc": "Get the URL for the previous request.",
            "long_desc": "",
            "hint": [
                [
                    "string",
                    false
                ]
            ],
            "hint_desc": "",
            "tags": [

            ],
            "modifiers": "1",
            "is_by_ref": "",
            "exceptions": [

            ],
            "errors": [

            ],
            "parameters": [

            ]
        },
        "to": {
            "name": "to",
            "line": 84,
            "short_desc": "Generate a absolute URL to the given path.",
            "long_desc": "",
            "hint": [
                [
                    "string",
                    false
                ]
            ],
            "hint_desc": "",
            "tags": [

            ],
            "modifiers": "1",
            "is_by_ref": "",
            "exceptions": [

            ],
            "errors": [

            ],
            "parameters": {
                "path": {
                    "name": "path",
                    "line": 84,
                    "short_desc": "",
                    "long_desc": null,
                    "hint": [
                        [
                            "string",
                            false
                        ]
                    ],
                    "tags": [

                    ],
                    "modifiers": "",
                    "default": null,
                    "is_by_ref": false
                },
                "parameters": {
                    "name": "parameters",
                    "line": 84,
                    "short_desc": "",
                    "long_desc": null,
                    "hint": [
                        [
                            "mixed",
                            false
                        ]
                    ],
                    "tags": [

                    ],
                    "modifiers": "",
                    "default": "array()",
                    "is_by_ref": false
                },
                "secure": {
                    "name": "secure",
                    "line": 84,
                    "short_desc": "",
                    "long_desc": null,
                    "hint": [
                        [
                            "bool",
                            false
                        ]
                    ],
                    "tags": [

                    ],
                    "modifiers": "",
                    "default": "null",
                    "is_by_ref": false
                }
            }
        },
        "secure": {
            "name": "secure",
            "line": 107,
            "short_desc": "Generate a secure, absolute URL to the given path.",
            "long_desc": "",
            "hint": [
                [
                    "string",
                    false
                ]
            ],
            "hint_desc": "",
            "tags": [

            ],
            "modifiers": "1",
            "is_by_ref": "",
            "exceptions": [

            ],
            "errors": [

            ],
            "parameters": {
                "path": {
                    "name": "path",
                    "line": 107,
                    "short_desc": "",
                    "long_desc": null,
                    "hint": [
                        [
                            "string",
                            false
                        ]
                    ],
                    "tags": [

                    ],
                    "modifiers": "",
                    "default": null,
                    "is_by_ref": false
                },
                "parameters": {
                    "name": "parameters",
                    "line": 107,
                    "short_desc": "",
                    "long_desc": null,
                    "hint": [
                        [
                            "array",
                            false
                        ]
                    ],
                    "tags": [

                    ],
                    "modifiers": "",
                    "default": "array()",
                    "is_by_ref": false
                }
            }
        },
        "asset": {
            "name": "asset",
            "line": 119,
            "short_desc": "Generate a URL to an application asset.",
            "long_desc": "",
            "hint": [
                [
                    "string",
                    false
                ]
            ],
            "hint_desc": "",
            "tags": [

            ],
            "modifiers": "1",
            "is_by_ref": "",
            "exceptions": [

            ],
            "errors": [

            ],
            "parameters": {
                "path": {
                    "name": "path",
                    "line": 119,
                    "short_desc": "",
                    "long_desc": null,
                    "hint": [
                        [
                            "string",
                            false
                        ]
                    ],
                    "tags": [

                    ],
                    "modifiers": "",
                    "default": null,
                    "is_by_ref": false
                },
                "secure": {
                    "name": "secure",
                    "line": 119,
                    "short_desc": "",
                    "long_desc": null,
                    "hint": [
                        [
                            "bool",
                            false
                        ]
                    ],
                    "tags": [

                    ],
                    "modifiers": "",
                    "default": "null",
                    "is_by_ref": false
                }
            }
        },
        "secureAsset": {
            "name": "secureAsset",
            "line": 150,
            "short_desc": "Generate a URL to a secure asset.",
            "long_desc": "",
            "hint": [
                [
                    "string",
                    false
                ]
            ],
            "hint_desc": "",
            "tags": [

            ],
            "modifiers": "1",
            "is_by_ref": "",
            "exceptions": [

            ],
            "errors": [

            ],
            "parameters": {
                "path": {
                    "name": "path",
                    "line": 150,
                    "short_desc": "",
                    "long_desc": null,
                    "hint": [
                        [
                            "string",
                            false
                        ]
                    ],
                    "tags": [

                    ],
                    "modifiers": "",
                    "default": null,
                    "is_by_ref": false
                }
            }
        },
        "route": {
            "name": "route",
            "line": 181,
            "short_desc": "Get the URL to a named route.",
            "long_desc": "",
            "hint": [
                [
                    "string",
                    false
                ]
            ],
            "hint_desc": "",
            "tags": [

            ],
            "modifiers": "1",
            "is_by_ref": "",
            "exceptions": [

            ],
            "errors": [

            ],
            "parameters": {
                "name": {
                    "name": "name",
                    "line": 181,
                    "short_desc": "",
                    "long_desc": null,
                    "hint": [
                        [
                            "string",
                            false
                        ]
                    ],
                    "tags": [

                    ],
                    "modifiers": "",
                    "default": null,
                    "is_by_ref": false
                },
                "parameters": {
                    "name": "parameters",
                    "line": 181,
                    "short_desc": "",
                    "long_desc": null,
                    "hint": [
                        [
                            "mixed",
                            false
                        ]
                    ],
                    "tags": [

                    ],
                    "modifiers": "",
                    "default": "array()",
                    "is_by_ref": false
                },
                "absolute": {
                    "name": "absolute",
                    "line": 181,
                    "short_desc": "",
                    "long_desc": null,
                    "hint": [
                        [
                            "bool",
                            false
                        ]
                    ],
                    "tags": [

                    ],
                    "modifiers": "",
                    "default": "true",
                    "is_by_ref": false
                }
            }
        },
        "action": {
            "name": "action",
            "line": 238,
            "short_desc": "Get the URL to a controller action.",
            "long_desc": "",
            "hint": [
                [
                    "string",
                    false
                ]
            ],
            "hint_desc": "",
            "tags": [

            ],
            "modifiers": "1",
            "is_by_ref": "",
            "exceptions": [

            ],
            "errors": [

            ],
            "parameters": {
                "action": {
                    "name": "action",
                    "line": 238,
                    "short_desc": "",
                    "long_desc": null,
                    "hint": [
                        [
                            "string",
                            false
                        ]
                    ],
                    "tags": [

                    ],
                    "modifiers": "",
                    "default": null,
                    "is_by_ref": false
                },
                "parameters": {
                    "name": "parameters",
                    "line": 238,
                    "short_desc": "",
                    "long_desc": null,
                    "hint": [
                        [
                            "mixed",
                            false
                        ]
                    ],
                    "tags": [

                    ],
                    "modifiers": "",
                    "default": "array()",
                    "is_by_ref": false
                },
                "absolute": {
                    "name": "absolute",
                    "line": 238,
                    "short_desc": "",
                    "long_desc": null,
                    "hint": [
                        [
                            "bool",
                            false
                        ]
                    ],
                    "tags": [

                    ],
                    "modifiers": "",
                    "default": "true",
                    "is_by_ref": false
                }
            }
        },
        "isValidUrl": {
            "name": "isValidUrl",
            "line": 287,
            "short_desc": "Determine if the given path is a valid URL.",
            "long_desc": "",
            "hint": [
                [
                    "bool",
                    false
                ]
            ],
            "hint_desc": "",
            "tags": [

            ],
            "modifiers": "1",
            "is_by_ref": "",
            "exceptions": [

            ],
            "errors": [

            ],
            "parameters": {
                "path": {
                    "name": "path",
                    "line": 287,
                    "short_desc": "",
                    "long_desc": null,
                    "hint": [
                        [
                            "string",
                            false
                        ]
                    ],
                    "tags": [

                    ],
                    "modifiers": "",
                    "default": null,
                    "is_by_ref": false
                }
            }
        },
        "getRequest": {
            "name": "getRequest",
            "line": 299,
            "short_desc": "Get the request instance.",
            "long_desc": "",
            "hint": [
                [
                    "\\Symfony\\Component\\HttpFoundation\\Request",
                    false
                ]
            ],
            "hint_desc": "",
            "tags": [

            ],
            "modifiers": "1",
            "is_by_ref": "",
            "exceptions": [

            ],
            "errors": [

            ],
            "parameters": [

            ]
        },
        "setRequest": {
            "name": "setRequest",
            "line": 310,
            "short_desc": "Set the current request instance.",
            "long_desc": "",
            "hint": [
                [
                    "void",
                    false
                ]
            ],
            "hint_desc": "",
            "tags": [

            ],
            "modifiers": "1",
            "is_by_ref": "",
            "exceptions": [

            ],
            "errors": [

            ],
            "parameters": {
                "request": {
                    "name": "request",
                    "line": 310,
                    "short_desc": "",
                    "long_desc": null,
                    "hint": [
                        [
                            "Symfony\\Component\\HttpFoundation\\Request",
                            false
                        ]
                    ],
                    "tags": [

                    ],
                    "modifiers": "Request",
                    "default": null,
                    "is_by_ref": false
                }
            }
        },
        "getGenerator": {
            "name": "getGenerator",
            "line": 326,
            "short_desc": "Get the Symfony URL generator instance.",
            "long_desc": "",
            "hint": [
                [
                    "\\Symfony\\Component\\Routing\\Generator\\UrlGenerator",
                    false
                ]
            ],
            "hint_desc": "",
            "tags": [

            ],
            "modifiers": "1",
            "is_by_ref": "",
            "exceptions": [

            ],
            "errors": [

            ],
            "parameters": [

            ]
        },
        "setGenerator": {
            "name": "setGenerator",
            "line": 337,
            "short_desc": "Set the Symfony URL generator instance.",
            "long_desc": "",
            "hint": [
                [
                    "void",
                    false
                ]
            ],
            "hint_desc": "",
            "tags": [

            ],
            "modifiers": "1",
            "is_by_ref": "",
            "exceptions": [

            ],
            "errors": [

            ],
            "parameters": {
                "generator": {
                    "name": "generator",
                    "line": 337,
                    "short_desc": "",
                    "long_desc": null,
                    "hint": [
                        [
                            "Symfony\\Component\\Routing\\Generator\\UrlGenerator",
                            false
                        ]
                    ],
                    "tags": [

                    ],
                    "modifiers": "SymfonyGenerator",
                    "default": null,
                    "is_by_ref": false
                }
            }
        }
    },
    "constants": [

    ]
}