{
    "name": "Illuminate\\Auth\\Console\\MakeRemindersCommand",
    "line": 8,
    "short_desc": "",
    "long_desc": "",
    "hint": null,
    "tags": [

    ],
    "namespace": "Illuminate\\Auth\\Console",
    "file": "\/media\/sf_Code\/Laravel\/api-gen\/src\/Illuminate\/Auth\/Console\/MakeRemindersCommand.php",
    "hash": "3e5a525b4c3e6e4b561c5ea1aa8d7ff5a75bc0c0",
    "parent": "Illuminate\\Console\\Command",
    "modifiers": 0,
    "is_trait": false,
    "is_interface": false,
    "aliases": {
        "Command": "Illuminate\\Console\\Command",
        "Filesystem": "Illuminate\\Filesystem\\Filesystem",
        "InputOption": "Symfony\\Component\\Console\\Input\\InputOption",
        "InputArgument": "Symfony\\Component\\Console\\Input\\InputArgument"
    },
    "errors": [

    ],
    "interfaces": [

    ],
    "properties": [

    ],
    "methods": {
        "__construct": {
            "name": "__construct",
            "line": 37,
            "short_desc": "Create a new reminder table command instance.",
            "long_desc": "",
            "hint": [
                [
                    "void",
                    false
                ]
            ],
            "hint_desc": "",
            "tags": [

            ],
            "modifiers": "1",
            "is_by_ref": "",
            "exceptions": [

            ],
            "errors": [

            ],
            "parameters": {
                "files": {
                    "name": "files",
                    "line": 37,
                    "short_desc": "",
                    "long_desc": null,
                    "hint": [
                        [
                            "Illuminate\\Filesystem\\Filesystem",
                            false
                        ]
                    ],
                    "tags": [

                    ],
                    "modifiers": "Filesystem",
                    "default": null,
                    "is_by_ref": false
                }
            }
        },
        "fire": {
            "name": "fire",
            "line": 49,
            "short_desc": "Execute the console command.",
            "long_desc": "",
            "hint": [
                [
                    "void",
                    false
                ]
            ],
            "hint_desc": "",
            "tags": [

            ],
            "modifiers": "1",
            "is_by_ref": "",
            "exceptions": [

            ],
            "errors": [

            ],
            "parameters": [

            ]
        }
    },
    "constants": [

    ]
}