{
    "name": "Illuminate\\Container\\Container",
    "line": 5,
    "short_desc": "",
    "long_desc": "",
    "hint": null,
    "tags": [

    ],
    "namespace": "Illuminate\\Container",
    "file": "\/media\/sf_Code\/Laravel\/api-gen\/src\/Illuminate\/Container\/Container.php",
    "hash": "3f18fc5cfbe1361ac1f014d5accfd7b1f077dc5a",
    "parent": null,
    "modifiers": 0,
    "is_trait": false,
    "is_interface": false,
    "aliases": {
        "Closure": "Closure",
        "ArrayAccess": "ArrayAccess",
        "ReflectionParameter": "ReflectionParameter"
    },
    "errors": [

    ],
    "interfaces": {
        "ArrayAccess": "ArrayAccess"
    },
    "properties": [

    ],
    "methods": {
        "bound": {
            "name": "bound",
            "line": 41,
            "short_desc": "Determine if the given abstract type has been bound.",
            "long_desc": "",
            "hint": [
                [
                    "bool",
                    false
                ]
            ],
            "hint_desc": "",
            "tags": [

            ],
            "modifiers": "1",
            "is_by_ref": "",
            "exceptions": [

            ],
            "errors": [

            ],
            "parameters": {
                "abstract": {
                    "name": "abstract",
                    "line": 41,
                    "short_desc": "",
                    "long_desc": null,
                    "hint": [
                        [
                            "string",
                            false
                        ]
                    ],
                    "tags": [

                    ],
                    "modifiers": "",
                    "default": null,
                    "is_by_ref": false
                }
            }
        },
        "bind": {
            "name": "bind",
            "line": 54,
            "short_desc": "Register a binding with the container.",
            "long_desc": "",
            "hint": [
                [
                    "void",
                    false
                ]
            ],
            "hint_desc": "",
            "tags": [

            ],
            "modifiers": "1",
            "is_by_ref": "",
            "exceptions": [

            ],
            "errors": [

            ],
            "parameters": {
                "abstract": {
                    "name": "abstract",
                    "line": 54,
                    "short_desc": "",
                    "long_desc": null,
                    "hint": [
                        [
                            "string",
                            false
                        ]
                    ],
                    "tags": [

                    ],
                    "modifiers": "",
                    "default": null,
                    "is_by_ref": false
                },
                "concrete": {
                    "name": "concrete",
                    "line": 54,
                    "short_desc": "",
                    "long_desc": null,
                    "hint": [
                        [
                            "Closure",
                            false
                        ],
                        [
                            "string",
                            false
                        ],
                        [
                            "null",
                            false
                        ]
                    ],
                    "tags": [

                    ],
                    "modifiers": "",
                    "default": "null",
                    "is_by_ref": false
                },
                "shared": {
                    "name": "shared",
                    "line": 54,
                    "short_desc": "",
                    "long_desc": null,
                    "hint": [
                        [
                            "bool",
                            false
                        ]
                    ],
                    "tags": [

                    ],
                    "modifiers": "",
                    "default": "false",
                    "is_by_ref": false
                }
            }
        },
        "bindIf": {
            "name": "bindIf",
            "line": 100,
            "short_desc": "Register a binding if it hasn't already been registered.",
            "long_desc": "",
            "hint": [
                [
                    "bool",
                    false
                ]
            ],
            "hint_desc": "",
            "tags": [

            ],
            "modifiers": "1",
            "is_by_ref": "",
            "exceptions": [

            ],
            "errors": [

            ],
            "parameters": {
                "abstract": {
                    "name": "abstract",
                    "line": 100,
                    "short_desc": "",
                    "long_desc": null,
                    "hint": [
                        [
                            "string",
                            false
                        ]
                    ],
                    "tags": [

                    ],
                    "modifiers": "",
                    "default": null,
                    "is_by_ref": false
                },
                "concrete": {
                    "name": "concrete",
                    "line": 100,
                    "short_desc": "",
                    "long_desc": null,
                    "hint": [
                        [
                            "Closure",
                            false
                        ],
                        [
                            "string",
                            false
                        ],
                        [
                            "null",
                            false
                        ]
                    ],
                    "tags": [

                    ],
                    "modifiers": "",
                    "default": "null",
                    "is_by_ref": false
                },
                "shared": {
                    "name": "shared",
                    "line": 100,
                    "short_desc": "",
                    "long_desc": null,
                    "hint": [
                        [
                            "bool",
                            false
                        ]
                    ],
                    "tags": [

                    ],
                    "modifiers": "",
                    "default": "false",
                    "is_by_ref": false
                }
            }
        },
        "singleton": {
            "name": "singleton",
            "line": 115,
            "short_desc": "Register a shared binding in the container.",
            "long_desc": "",
            "hint": [
                [
                    "void",
                    false
                ]
            ],
            "hint_desc": "",
            "tags": [

            ],
            "modifiers": "1",
            "is_by_ref": "",
            "exceptions": [

            ],
            "errors": [

            ],
            "parameters": {
                "abstract": {
                    "name": "abstract",
                    "line": 115,
                    "short_desc": "",
                    "long_desc": null,
                    "hint": [
                        [
                            "string",
                            false
                        ]
                    ],
                    "tags": [

                    ],
                    "modifiers": "",
                    "default": null,
                    "is_by_ref": false
                },
                "concrete": {
                    "name": "concrete",
                    "line": 115,
                    "short_desc": "",
                    "long_desc": null,
                    "hint": [
                        [
                            "Closure",
                            false
                        ],
                        [
                            "string",
                            false
                        ],
                        [
                            "null",
                            false
                        ]
                    ],
                    "tags": [

                    ],
                    "modifiers": "",
                    "default": "null",
                    "is_by_ref": false
                }
            }
        },
        "share": {
            "name": "share",
            "line": 126,
            "short_desc": "Wrap a Closure such that it is shared.",
            "long_desc": "",
            "hint": [
                [
                    "Closure",
                    false
                ]
            ],
            "hint_desc": "",
            "tags": [

            ],
            "modifiers": "1",
            "is_by_ref": "",
            "exceptions": [

            ],
            "errors": [

            ],
            "parameters": {
                "closure": {
                    "name": "closure",
                    "line": 126,
                    "short_desc": "",
                    "long_desc": null,
                    "hint": [
                        [
                            "Closure",
                            false
                        ]
                    ],
                    "tags": [

                    ],
                    "modifiers": "Closure",
                    "default": null,
                    "is_by_ref": false
                }
            }
        },
        "extend": {
            "name": "extend",
            "line": 151,
            "short_desc": "\"Extend\" an abstract type in the container.",
            "long_desc": "",
            "hint": [
                [
                    "void",
                    false
                ]
            ],
            "hint_desc": "",
            "tags": [

            ],
            "modifiers": "1",
            "is_by_ref": "",
            "exceptions": [

            ],
            "errors": [

            ],
            "parameters": {
                "abstract": {
                    "name": "abstract",
                    "line": 151,
                    "short_desc": "",
                    "long_desc": null,
                    "hint": [
                        [
                            "string",
                            false
                        ]
                    ],
                    "tags": [

                    ],
                    "modifiers": "",
                    "default": null,
                    "is_by_ref": false
                },
                "closure": {
                    "name": "closure",
                    "line": 151,
                    "short_desc": "",
                    "long_desc": null,
                    "hint": [
                        [
                            "Closure",
                            false
                        ]
                    ],
                    "tags": [

                    ],
                    "modifiers": "Closure",
                    "default": null,
                    "is_by_ref": false
                }
            }
        },
        "instance": {
            "name": "instance",
            "line": 177,
            "short_desc": "Register an existing instance as shared in the container.",
            "long_desc": "",
            "hint": [
                [
                    "void",
                    false
                ]
            ],
            "hint_desc": "",
            "tags": [

            ],
            "modifiers": "1",
            "is_by_ref": "",
            "exceptions": [

            ],
            "errors": [

            ],
            "parameters": {
                "abstract": {
                    "name": "abstract",
                    "line": 177,
                    "short_desc": "",
                    "long_desc": null,
                    "hint": [
                        [
                            "string",
                            false
                        ]
                    ],
                    "tags": [

                    ],
                    "modifiers": "",
                    "default": null,
                    "is_by_ref": false
                },
                "instance": {
                    "name": "instance",
                    "line": 177,
                    "short_desc": "",
                    "long_desc": null,
                    "hint": [
                        [
                            "mixed",
                            false
                        ]
                    ],
                    "tags": [

                    ],
                    "modifiers": "",
                    "default": null,
                    "is_by_ref": false
                }
            }
        },
        "alias": {
            "name": "alias",
            "line": 196,
            "short_desc": "Alias a type to a shorter name.",
            "long_desc": "",
            "hint": [
                [
                    "void",
                    false
                ]
            ],
            "hint_desc": "",
            "tags": [

            ],
            "modifiers": "1",
            "is_by_ref": "",
            "exceptions": [

            ],
            "errors": [

            ],
            "parameters": {
                "abstract": {
                    "name": "abstract",
                    "line": 196,
                    "short_desc": "",
                    "long_desc": null,
                    "hint": [
                        [
                            "string",
                            false
                        ]
                    ],
                    "tags": [

                    ],
                    "modifiers": "",
                    "default": null,
                    "is_by_ref": false
                },
                "alias": {
                    "name": "alias",
                    "line": 196,
                    "short_desc": "",
                    "long_desc": null,
                    "hint": [
                        [
                            "string",
                            false
                        ]
                    ],
                    "tags": [

                    ],
                    "modifiers": "",
                    "default": null,
                    "is_by_ref": false
                }
            }
        },
        "make": {
            "name": "make",
            "line": 219,
            "short_desc": "Resolve the given type from the container.",
            "long_desc": "",
            "hint": [
                [
                    "mixed",
                    false
                ]
            ],
            "hint_desc": "",
            "tags": [

            ],
            "modifiers": "1",
            "is_by_ref": "",
            "exceptions": [

            ],
            "errors": [

            ],
            "parameters": {
                "abstract": {
                    "name": "abstract",
                    "line": 219,
                    "short_desc": "",
                    "long_desc": null,
                    "hint": [
                        [
                            "string",
                            false
                        ]
                    ],
                    "tags": [

                    ],
                    "modifiers": "",
                    "default": null,
                    "is_by_ref": false
                },
                "parameters": {
                    "name": "parameters",
                    "line": 219,
                    "short_desc": "",
                    "long_desc": null,
                    "hint": [
                        [
                            "array",
                            false
                        ]
                    ],
                    "tags": [

                    ],
                    "modifiers": "",
                    "default": "array()",
                    "is_by_ref": false
                }
            }
        },
        "build": {
            "name": "build",
            "line": 286,
            "short_desc": "Instantiate a concrete instance of the given type.",
            "long_desc": "",
            "hint": [
                [
                    "mixed",
                    false
                ]
            ],
            "hint_desc": "",
            "tags": [

            ],
            "modifiers": "1",
            "is_by_ref": "",
            "exceptions": [

            ],
            "errors": [

            ],
            "parameters": {
                "concrete": {
                    "name": "concrete",
                    "line": 286,
                    "short_desc": "",
                    "long_desc": null,
                    "hint": [
                        [
                            "string",
                            false
                        ]
                    ],
                    "tags": [

                    ],
                    "modifiers": "",
                    "default": null,
                    "is_by_ref": false
                },
                "parameters": {
                    "name": "parameters",
                    "line": 286,
                    "short_desc": "",
                    "long_desc": null,
                    "hint": [
                        [
                            "array",
                            false
                        ]
                    ],
                    "tags": [

                    ],
                    "modifiers": "",
                    "default": "array()",
                    "is_by_ref": false
                }
            }
        },
        "resolving": {
            "name": "resolving",
            "line": 384,
            "short_desc": "Register a new resolving callback.",
            "long_desc": "",
            "hint": [
                [
                    "void",
                    false
                ]
            ],
            "hint_desc": "",
            "tags": [

            ],
            "modifiers": "1",
            "is_by_ref": "",
            "exceptions": [

            ],
            "errors": [

            ],
            "parameters": {
                "callback": {
                    "name": "callback",
                    "line": 384,
                    "short_desc": "",
                    "long_desc": null,
                    "hint": [
                        [
                            "Closure",
                            false
                        ]
                    ],
                    "tags": [

                    ],
                    "modifiers": "Closure",
                    "default": null,
                    "is_by_ref": false
                }
            }
        },
        "getBindings": {
            "name": "getBindings",
            "line": 444,
            "short_desc": "Get the container's bindings.",
            "long_desc": "",
            "hint": [
                [
                    "array",
                    false
                ]
            ],
            "hint_desc": "",
            "tags": [

            ],
            "modifiers": "1",
            "is_by_ref": "",
            "exceptions": [

            ],
            "errors": [

            ],
            "parameters": [

            ]
        },
        "offsetExists": {
            "name": "offsetExists",
            "line": 455,
            "short_desc": "Determine if a given offset exists.",
            "long_desc": "",
            "hint": [
                [
                    "bool",
                    false
                ]
            ],
            "hint_desc": "",
            "tags": [

            ],
            "modifiers": "1",
            "is_by_ref": "",
            "exceptions": [

            ],
            "errors": [

            ],
            "parameters": {
                "key": {
                    "name": "key",
                    "line": 455,
                    "short_desc": "",
                    "long_desc": null,
                    "hint": [
                        [
                            "string",
                            false
                        ]
                    ],
                    "tags": [

                    ],
                    "modifiers": "",
                    "default": null,
                    "is_by_ref": false
                }
            }
        },
        "offsetGet": {
            "name": "offsetGet",
            "line": 466,
            "short_desc": "Get the value at a given offset.",
            "long_desc": "",
            "hint": [
                [
                    "mixed",
                    false
                ]
            ],
            "hint_desc": "",
            "tags": [

            ],
            "modifiers": "1",
            "is_by_ref": "",
            "exceptions": [

            ],
            "errors": [

            ],
            "parameters": {
                "key": {
                    "name": "key",
                    "line": 466,
                    "short_desc": "",
                    "long_desc": null,
                    "hint": [
                        [
                            "string",
                            false
                        ]
                    ],
                    "tags": [

                    ],
                    "modifiers": "",
                    "default": null,
                    "is_by_ref": false
                }
            }
        },
        "offsetSet": {
            "name": "offsetSet",
            "line": 478,
            "short_desc": "Set the value at a given offset.",
            "long_desc": "",
            "hint": [
                [
                    "void",
                    false
                ]
            ],
            "hint_desc": "",
            "tags": [

            ],
            "modifiers": "1",
            "is_by_ref": "",
            "exceptions": [

            ],
            "errors": [

            ],
            "parameters": {
                "key": {
                    "name": "key",
                    "line": 478,
                    "short_desc": "",
                    "long_desc": null,
                    "hint": [
                        [
                            "string",
                            false
                        ]
                    ],
                    "tags": [

                    ],
                    "modifiers": "",
                    "default": null,
                    "is_by_ref": false
                },
                "value": {
                    "name": "value",
                    "line": 478,
                    "short_desc": "",
                    "long_desc": null,
                    "hint": [
                        [
                            "mixed",
                            false
                        ]
                    ],
                    "tags": [

                    ],
                    "modifiers": "",
                    "default": null,
                    "is_by_ref": false
                }
            }
        },
        "offsetUnset": {
            "name": "offsetUnset",
            "line": 500,
            "short_desc": "Unset the value at a given offset.",
            "long_desc": "",
            "hint": [
                [
                    "void",
                    false
                ]
            ],
            "hint_desc": "",
            "tags": [

            ],
            "modifiers": "1",
            "is_by_ref": "",
            "exceptions": [

            ],
            "errors": [

            ],
            "parameters": {
                "key": {
                    "name": "key",
                    "line": 500,
                    "short_desc": "",
                    "long_desc": null,
                    "hint": [
                        [
                            "string",
                            false
                        ]
                    ],
                    "tags": [

                    ],
                    "modifiers": "",
                    "default": null,
                    "is_by_ref": false
                }
            }
        }
    },
    "constants": [

    ]
}